pytacite/__init__.py
pytacite/_version.py
pytacite/api.py
pytacite/base.py
pytacite-0.5.1.dist-info/LICENSE
pytacite-0.5.1.dist-info/METADATA
pytacite-0.5.1.dist-info/WHEEL
pytacite-0.5.1.dist-info/top_level.txt
pytacite-0.5.1.dist-info/RECORD
