Metadata-Version: 2.1
Name: pytacite
Version: 0.5.1
Summary: A flexible and lightweight Python interface to the DataCite database
Author-email: Jonathan de Bruin <jonathandebruinos@gmail.com>
License: MIT
Classifier: Development Status :: 4 - Beta
Classifier: License :: OSI Approved :: MIT License
Classifier: Programming Language :: Python :: 3.8
Classifier: Programming Language :: Python :: 3.9
Classifier: Programming Language :: Python :: 3.10
Classifier: Programming Language :: Python :: 3.11
Classifier: Programming Language :: Python :: 3.12
Requires-Python: >=3.8
License-File: LICENSE
Requires-Dist: requests
Provides-Extra: lint
Requires-Dist: ruff ; extra == 'lint'
Requires-Dist: black ; extra == 'lint'
Provides-Extra: test
Requires-Dist: pytest ; extra == 'test'
